{
    "created_at": "Fri, 07 Jun 2013 17:01:03 +0000",
    "from_user": "EmmaLee_Anne",
    "from_user_id": 552270433,
    "from_user_name": "Emily Anne ♥ ",
    "id": 343049981277646850,
    "source": "&lt;a href=&quot;http://twitter.com/download/android&quot;&gt;Twitter for Android&lt;/a&gt;",
    "text": "RT @itsesmiibruh: why do girls in tampon commercials seem so happy? i am never happy when i'm on my period.",

    "language": "EN",
    
    "tokens": [
      {
        "lemma": "RT",
        "normalized": "RT",
        "token": "RT",
        "bnsense": "",
        "type": "token",
        "pos": "~",
      },
      {
        "lemma": "@itsesmiibruh",
        "normalized": "@itsesmiibruh",
        "token": "@itsesmiibruh",
        "bnsense": "",
        "type": "token",
        "pos": "@",
      },
      {
        "lemma": ":",
        "normalized": ":",
        "token": ":",
        "bnsense": "",
        "type": "token",
        "pos": "~",
      },
      {
        "lemma": "why",
        "normalized": "why",
        "token": "why",
        "bnsense": "",
        "type": "token",
        "pos": "R",
      },
      {
        "lemma": "do",
        "normalized": "do",
        "token": "do",
        "bnsense": "",
        "type": "token",
        "pos": "V",
      },
      {
        "lemma": "girl",
        "normalized": "girls",
        "token": "girls",
        "bnsense": "bn:00034453n",
        "type": "token",
        "pos": "N",
      },
      {
        "lemma": "in",
        "normalized": "in",
        "token": "in",
        "bnsense": "",
        "type": "token",
        "pos": "P",
      },
      {
        "lemma": "tampon",
        "normalized": "tampon",
        "token": "tampon",
        "bnsense": "bn:00076017n",
        "type": "token",
        "pos": "N",
      },
      {
        "lemma": "commercial",
        "normalized": "commercials",
        "token": "commercials",
        "bnsense": "bn:00020987n",
        "type": "token",
        "pos": "N",
      },
      {
        "lemma": "seem",
        "normalized": "seem",
        "token": "seem",
        "bnsense": "bn:00082693v",
        "type": "token",
        "pos": "V",
      },
      {
        "lemma": "so",
        "normalized": "so",
        "token": "so",
        "bnsense": "bn:00117043r",
        "type": "token",
        "pos": "R",
      },
      {
        "lemma": "happy",
        "normalized": "happy",
        "token": "happy",
        "bnsense": "bn:00103933a",
        "type": "token",
        "pos": "A",
      },
      {
        "lemma": "?",
        "normalized": "?",
        "token": "?",
        "bnsense": "",
        "type": "token",
        "pos": ",",
      },
      {
        "lemma": "I",
        "normalized": "I",
        "token": "i",
        "bnsense": "",
        "type": "token",
        "pos": "O",
      },
      {
        "lemma": "be",
        "normalized": "am",
        "token": "am",
        "bnsense": "bn:00083181v",
        "type": "token",
        "pos": "V",
      },
      {
        "lemma": "never",
        "normalized": "never",
        "token": "never",
        "bnsense": "bn:00116326r",
        "type": "token",
        "pos": "R",
      },
      {
        "lemma": "happy",
        "normalized": "happy",
        "token": "happy",
        "bnsense": "bn:00103933a",
        "type": "token",
        "pos": "A",
      },
      {
        "lemma": "when",
        "normalized": "when",
        "token": "when",
        "bnsense": "",
        "type": "token",
        "pos": "P",
      },
      {
        "token": "I'm",
        "type": "MME",
        "expansion": [
          {
	    "token": "I",
	    "normalized": "I",
	    "lemma": "I",
	    "pos": "O",
	    "bnsense": "",
          },
          {
	    "token": "'m",
	    "normalized": "am",
	    "lemma": "be",
	    "pos": "V",
	    "bnsense": "bn:00083181v",
          }
        ],
      },
      {
        "lemma": "on",
        "normalized": "on",
        "token": "on",
        "bnsense": "",
        "type": "token",
        "pos": "P",
      },
      {
        "lemma": "my",
        "normalized": "my",
        "token": "my",
        "bnsense": "",
        "type": "token",
        "pos": "D",
      },
      {
        "lemma": "period",
        "normalized": "period",
        "token": "period",
        "bnsense": "bn:00016665n",
        "type": "token",
        "pos": "N",
      },
      {
        "lemma": ".",
        "normalized": ".",
        "token": ".",
        "bnsense": "",
        "type": "token",
        "pos": ",",
      },
    ],
    
    "type": ["Subjective", "Deliberative", "Identification"],
    "categories": ["Health", "Women's Health"],
    
    "paraphrases": [
	{
	    "text": "Why are girls in tampon commercials always very happy?",
	    "rating": 4.8
	},

	{
	    "text": "Why are girls and women in tampon commercials happy?",
	    "rating": 4.8
	},
	
	{
	    "text": "Why do girls in tampon commercials dance and laugh around happily?",
	    "rating": 4.0
	}
    ],
    
    "qpairs": [
	{
	    "question": "Why is it that girls in tampon commercials are laughing and dancing?",
	    "answer": "Because they are commercials and just interested in selling stuff so they make things up and make everyone look ridiculously happy even when there really isn't anything to be happy about.",
	    "url": "http://answers.yahoo.com/question/index;_ylt=AsPDYxiLGF0mGdXVU.HS88sjzKIX;_ylv=3?qid=20130514181539AAqKMzl",
	    
	    "sentiment": {
		"class": "Neutral",
		"score": 0.75
	    },
	    
	    "similarity": 3.9,
	    
	    "simplified_answer": "Because commercials are just interested in selling stuff so they make things up and make everyone look happy even when there really isn't anything to be happy about.",
	    "summarized_answer": "Because commercials are just interested in selling stuff, so they make things up and make everyone look happy."
	},
	
	{
	    "question": "Why is it that in Tampon Commercials the females are always laughing & dancing around??",
	    "answer": " I agree with you. But if they showed us weeping and breaking dishes, they wouldn't sell many tampons.",
	    "url": "http://www.answerbag.com/q_view/2760817",
	    
	    "sentiment": {
		"class": "Neutral",
		"score": 0.8
	    },
	    
	    "similarity": 3.2,
	    
	    "simplified_answer": "But if they showed girls weeping and breaking dishes, they wouldn't sell many tampons.",
	    "summarized_answer": "If they showed girls weeping and breaking dishes, they wouldn't sell many tampons.."
	}
    ],
    
    "qrel": ["what", "reason of", "happy girls in tampon commercials"]
}
